webq/__init__.py
webq/api.py
webq/app.py
webq/config.py
webq/context.py
webq/db.py
webq/log.py
webq/main.py
webq/model/__init__.py
webq/model/db.py
webq/model/dto.py
webq/service.py
webq/storage.py
webq/util.py
webq-0.0.3.dist-info/METADATA
webq-0.0.3.dist-info/WHEEL
webq-0.0.3.dist-info/entry_points.txt
webq-0.0.3.dist-info/RECORD
